capture_db_queries/__init__.py
capture_db_queries/_logging.py
capture_db_queries/_sqlite3_adapters_and_converters.py
capture_db_queries/decorators.py
capture_db_queries/dtos.py
capture_db_queries/handlers.py
capture_db_queries/printers.py
capture_db_queries/settings.py
capture_db_queries/timers.py
capture_db_queries/types.py
capture_db_queries/wrappers.py
capture_db_queries-1.2.8.dist-info/LICENSE
capture_db_queries-1.2.8.dist-info/METADATA
capture_db_queries-1.2.8.dist-info/WHEEL
capture_db_queries-1.2.8.dist-info/entry_points.txt
capture_db_queries-1.2.8.dist-info/top_level.txt
capture_db_queries-1.2.8.dist-info/RECORD
