Metadata-Version: 2.2
Name: capture_db_queries
Version: 1.2.8
Summary: Decorator for measuring the time and number of database queries
Home-page: https://github.com/Friskes/capture-db-queries
Author: Friskes
Author-email: Friskes <friskesx@gmail.com>
License: MIT License
Project-URL: Homepage, https://github.com/Friskes/capture-db-queries
Project-URL: Changelog, https://github.com/Friskes/capture-db-queries/releases/
Project-URL: Issues, https://github.com/Friskes/capture-db-queries/issues
Keywords: Django,Database
Classifier: Development Status :: 5 - Production/Stable
Classifier: Environment :: Web Environment
Classifier: Intended Audience :: Developers
Classifier: Operating System :: OS Independent
Classifier: License :: OSI Approved :: MIT License
Classifier: Programming Language :: Python :: 3.8
Classifier: Programming Language :: Python :: 3.9
Classifier: Programming Language :: Python :: 3.10
Classifier: Programming Language :: Python :: 3.11
Classifier: Programming Language :: Python :: 3.12
Classifier: Framework :: Django :: 3.2
Classifier: Framework :: Django :: 4.0
Classifier: Framework :: Django :: 4.1
Classifier: Framework :: Django :: 4.2
Classifier: Topic :: Internet :: WWW/HTTP
Classifier: Topic :: Documentation
Classifier: Topic :: Software Development :: Code Generators
Requires-Python: >=3.8
License-File: LICENSE
Requires-Dist: django>=3.2.25
Requires-Dist: sqlparse>=0.4.4
Requires-Dist: pygments>=2.17.2
Provides-Extra: dev
Requires-Dist: pytest-django>=4.8.0; extra == "dev"
Requires-Dist: pre-commit>=3.5.0; extra == "dev"
Requires-Dist: ruff==0.8.0; extra == "dev"
Requires-Dist: pytest>=7.0.1; extra == "dev"
Requires-Dist: mypy>=1.10.0; extra == "dev"
Requires-Dist: pytest-cov>=5.0.0; extra == "dev"
Provides-Extra: ci
Requires-Dist: pytest-django>=4.8.0; extra == "ci"
Requires-Dist: ruff==0.8.0; extra == "ci"
Requires-Dist: pytest>=7.0.1; extra == "ci"
Requires-Dist: mypy>=1.10.0; extra == "ci"
Requires-Dist: pytest-cov>=5.0.0; extra == "ci"
